betweens/__init__.py
betweens/betweens.py
betweens/version.py
betweens-1.2.2.dist-info/LICENSE
betweens-1.2.2.dist-info/METADATA
betweens-1.2.2.dist-info/WHEEL
betweens-1.2.2.dist-info/top_level.txt
betweens-1.2.2.dist-info/RECORD
